tsc/__init__.py
tsc/utils/__init__.py
tsc/utils/chopin.mp3
tsc/utils/compression.py
tsc/utils/compression_pipelines.py
tsc/utils/data.py
tsc/utils/helper_functions.py
tsc/utils/reconstruction.py
tsc/utils/viz.py
topological_signal_compression-0.11.2.dist-info/LICENSE
topological_signal_compression-0.11.2.dist-info/METADATA
topological_signal_compression-0.11.2.dist-info/WHEEL
topological_signal_compression-0.11.2.dist-info/top_level.txt
topological_signal_compression-0.11.2.dist-info/RECORD
