Metadata-Version: 2.1
Name: topological-signal-compression
Version: 0.11.2
Summary: Topological Signal Compression
Author-email: Gary Koplik <gary.koplik@geomdata.com>
License: GNU AGPL
Project-URL: Documentation, https://geomdata.gitlab.io/topological-signal-compression/index.html
Project-URL: Source, https://gitlab.com/geomdata/topological-signal-compression
Requires-Python: >=3.11
License-File: LICENSE
Requires-Dist: gda-public
Requires-Dist: numpy
Provides-Extra: docs
Requires-Dist: nbsphinx; extra == "docs"
Requires-Dist: sphinx; extra == "docs"
Requires-Dist: sphinx-rtd-theme; extra == "docs"
Requires-Dist: toml; extra == "docs"
Provides-Extra: extras
Requires-Dist: kymatio; extra == "extras"
Requires-Dist: matplotlib; extra == "extras"
Requires-Dist: pydub; extra == "extras"
Requires-Dist: pyts; extra == "extras"
Provides-Extra: ruff
Requires-Dist: ruff; extra == "ruff"
Provides-Extra: testing
Requires-Dist: pytest; extra == "testing"
Requires-Dist: pytest-cov; extra == "testing"
Requires-Dist: pytest-html; extra == "testing"
Requires-Dist: pytest-timeout; extra == "testing"
Requires-Dist: pytest-xdist; extra == "testing"
